README.rst
setup.cfg
setup.py
phaxio/__init__.py
phaxio/api.py
phaxio/exceptions.py
phaxio.egg-info/PKG-INFO
phaxio.egg-info/SOURCES.txt
phaxio.egg-info/dependency_links.txt
phaxio.egg-info/requires.txt
phaxio.egg-info/top_level.txt
phaxio/swagger_client/__init__.py
phaxio/swagger_client/api_client.py
phaxio/swagger_client/configuration.py
phaxio/swagger_client/rest.py
phaxio/swagger_client/apis/__init__.py
phaxio/swagger_client/apis/default_api.py
phaxio/swagger_client/models/__init__.py
phaxio/swagger_client/models/account_status.py
phaxio/swagger_client/models/account_status_data.py
phaxio/swagger_client/models/area_code.py
phaxio/swagger_client/models/country.py
phaxio/swagger_client/models/error.py
phaxio/swagger_client/models/fax_info.py
phaxio/swagger_client/models/generate_phax_code_json_response.py
phaxio/swagger_client/models/generate_phax_code_json_response_data.py
phaxio/swagger_client/models/get_area_codes_response.py
phaxio/swagger_client/models/get_countries_response.py
phaxio/swagger_client/models/get_fax_info_response.py
phaxio/swagger_client/models/get_faxes_response.py
phaxio/swagger_client/models/list_phone_numbers_response.py
phaxio/swagger_client/models/operation_status.py
phaxio/swagger_client/models/paging.py
phaxio/swagger_client/models/phax_code.py
phaxio/swagger_client/models/phax_code_data.py
phaxio/swagger_client/models/phone_number.py
phaxio/swagger_client/models/phone_number_response.py
phaxio/swagger_client/models/recipient.py
phaxio/swagger_client/models/send_fax_response.py
phaxio/swagger_client/models/send_fax_response_data.py
phaxio/swagger_client/models/status.py
tests/__init__.py
tests/test_api.py
tests/unit_tests.py