Metadata-Version: 1.1
Name: phaxio
Version: 0.3
Summary: Python client for Phaxio v2 API
Home-page: https://github.com/anpolsky/phaxio-python
Author: Aryeh Polsky
Author-email: anpolsky@gmail.com
License: MIT License
Keywords: python phaxio fax api
Platform: UNKNOWN
Classifier: Programming Language :: Python
Classifier: Programming Language :: Python :: 3
Classifier: Programming Language :: Python :: 2
